datalib/__init__.py
datalib/analysis.py
datalib/data_processing.py
datalib/reinforcement.py
datalib/statistics.py
datalib/supervised.py
datalib/unsupervised.py
datalib/visualization.py
oussama_datalib-0.2.2.dist-info/entry_points.txt
oussama_datalib-0.2.2.dist-info/LICENSE
oussama_datalib-0.2.2.dist-info/METADATA
oussama_datalib-0.2.2.dist-info/WHEEL
oussama_datalib-0.2.2.dist-info/RECORD
