Metadata-Version: 2.1
Name: oussama_datalib
Version: 0.2.2
Summary: Simplified data manipulation and analysis tools
Home-page: https://github.com/elayeboussama/oussama_datalib
License: MIT
Keywords: data,analysis,machine learning,visualization
Author: Oussama ELAYEB
Author-email: elayeb.oussama2020@gmail.com
Requires-Python: >=3.10,<4.0
Classifier: Development Status :: 3 - Alpha
Classifier: Intended Audience :: Developers
Classifier: License :: OSI Approved :: MIT License
Classifier: Programming Language :: Python :: 3
Classifier: Programming Language :: Python :: 3.10
Classifier: Programming Language :: Python :: 3.11
Classifier: Programming Language :: Python :: 3.12
Classifier: Programming Language :: Python :: 3.13
Classifier: Topic :: Scientific/Engineering :: Artificial Intelligence
Classifier: Topic :: Scientific/Engineering :: Visualization
Requires-Dist: matplotlib (>=3.4.0)
Requires-Dist: numpy (>=1.21.0)
Requires-Dist: pandas (>=2.2.3,<3.0.0)
Requires-Dist: scikit-learn (>=1.0.0)
Requires-Dist: scipy (>=1.7.0)
Requires-Dist: seaborn (>=0.11.0)
Project-URL: Repository, https://github.com/elayeboussama/oussama_datalib
